coci/__init__.py
coci/__main__.py
coci/main.py
coci-0.2.0.dist-info/LICENSE
coci-0.2.0.dist-info/METADATA
coci-0.2.0.dist-info/WHEEL
coci-0.2.0.dist-info/top_level.txt
coci-0.2.0.dist-info/RECORD
