Metadata-Version: 2.1
Name: coci
Version: 0.2.0
Summary: Collective Observation on Causal Inference
Home-page: UNKNOWN
Author: Koki Fujiwara
Author-email: koki.fujiwara@exwzd.com
License: UNKNOWN
Platform: UNKNOWN
Requires-Dist: numpy
Requires-Dist: seaborn
